vector/__init__.py
vector/assistive_functions.py
vector/color.py
vector/vector2d.py
vector/vector3d.py
hamolicious_vector_class-1.2.0.dist-info/LICENSE
hamolicious_vector_class-1.2.0.dist-info/METADATA
hamolicious_vector_class-1.2.0.dist-info/WHEEL
hamolicious_vector_class-1.2.0.dist-info/top_level.txt
hamolicious_vector_class-1.2.0.dist-info/RECORD
