Metadata-Version: 2.1
Name: hamolicious-vector-class
Version: 1.2.0
Summary: A small and simple vector class
Home-page: https://github.com/hamolicious/Vector-Class
Author: Hamolicous
License: UNKNOWN
Project-URL: Bug Tracker, https://github.com/hamolicious/Vector-Class/issues
Platform: UNKNOWN
Classifier: Programming Language :: Python :: 3
Classifier: License :: OSI Approved :: MIT License
Classifier: Operating System :: OS Independent
Requires-Python: >=3.6
License-File: LICENSE
